{
    "basics": {
        "name": "Chris J. Kolenko",
        "label": "Principal DevOps Engineer / Principal Systems Engineer",
        "image": "assets/headshot.jpg",
        "email": "chris@webcanvas.com.au",
        "phone": "+61 412 149 906",
        "summary": "I have a proven track record of delivering complex projects and leading teams to success. I have a strong background in DevOps, Cloud, Platform Engineering and Software Development. I have a passion for building high performing teams and delivering business value through technology.",
        "location": {
            "city": "Sydney",
            "countryCode": "AU"
        },
        "profiles": [
            {
                "network": "GitHub",
                "username": "chriskolenko",
                "url": "https://github.com/chriskolenko"
            }
        ]
    },
    "work": [
        {
            "company": "WooliesX",
            "location": "Sydney/Remote",
            "position": "Lead Cloud Platform Engineer",
            "summary": "Specialising in GCP and Platform Engineering",
            "startDate": "2022-12",
            "keywords": [
                "GCP",
                "Agile",
                "DevOps",
                "Terraform"
            ],
            "highlights": [
                "Worked with Woolworths Group to create complex IHLDs (Infrastructure High Level Designs) for cross cloud connectivity",
                "Design patterns for GCP consumption as a service",
                "Support delivery teams with best practices",
                "Support delivery teams with production deployments and incident triage",
                "Reduce risk in I.T. systems across various domains"
            ]
        },
        {
            "company": "Rackspace",
            "location": "Sydney/Remote",
            "position": "Lead Cloud Architect Consultant",
            "summary": "Joined the Elastic Engineering APJ department to run a team of highly skilled DevOps, Cloud and Platform engineers",
            "startDate": "2021-07",
            "endDate": "2022-12",
            "keywords": [
                "AWS",
                "GCP",
                "Agile",
                "DevOps",
                "Terraform",
                "Kubernetes",
                "Observability",
                "Packer"
            ],
            "highlights": [
                "Built multiple DevOps teams up to 10 engineers during volatile and competitive market conditions",
                "Managed 12+ businesses of varying sizes across multiple industries",
                "Created skills matrix, development plans, modernized the interview process",
                "Worked with 12+ Companies from Startup to Large Enterprise",
                "Built strategies for standardising and modularising I.T. infrastructure",
                "Ensured our deliverables met strong industry standards; Security, Cost, Performance, Reliability and Scalability",
                "In charge of overall Architecture of all projects my team was involved in"
            ]
        },
        {
            "breakBefore": true,
            "company": "Hyphen Group (Compare Asia Group)",
            "location": "Remote",
            "position": "Head of Platform",
            "summary": "Built multiple teams responsible for Cyber Security, ITSM, Test Automation and DevOps",
            "startDate": "2021-02",
            "endDate": "2021-07",
            "keywords": [
                "AWS",
                "Cyber Security",
                "ITSM",
                "Vendor Management",
                "Testing",
                "DevOps",
                "Platform"
            ],
            "highlights": [
                "Hired multiple Cyber Security engineers and built the strategy",
                "Developed multiple individuals into leadership roles",
                "Built the ITSM team to in-house I.T. Support",
                "Introduced multiple vendors to solve problems with Monitoring and Security"
            ]
        },
        {
            "company": "Hyphen Group (Compare Asia Group)",
            "location": "Remote",
            "position": "Head of DevOps",
            "summary": "Built multiple teams responsible for DevOps, AWS infrastructure and SRE",
            "startDate": "2019-02",
            "endDate": "2021-02",
            "keywords": [
                "AWS",
                "Kubernetes",
                "CI/CD",
                "GitOps",
                "Automation",
                "Leadership",
                "Golang"
            ],
            "highlights": [
                "Architected and designed the AWS infrastructure",
                "Architected and designed how applications communicated with each other",
                "Transformed multiple AWS environments using Kubernetes, GitOps and Agile",
                "Scaled up to 10 production Kubernetes clusters",
                "Built and hired the DevOps/System Engineers",
                "Built and hired the SRE team",
                "Responsible for short, mid and long term strategy",
                "Introduced DataDog for monitoring and logging",
                "Custom built deployment tooling to convert services into Containers using Golang"
            ]
        },
        {
            "company": "Industrie and Co",
            "location": "Sydney",
            "position": "DevOps Practice Lead",
            "summary": "Lead a team of 6 DevOps engineers and engaged with clients to deliver projects through to production",
            "startDate": "2018-07",
            "endDate": "2019-02",
            "keywords": [
                "AWS",
                "Terraform",
                "DevOps",
                "Kubernetes",
                "AWS"
            ],
            "highlights": [
                "Design and implement a bank grade network in AWS",
                "Production Kubernetes cluster using an Istio service mesh",
                "Designed and implement VPN strategy to access private networks and development environments",
                "Design and implement logging and monitoring strategies",
                "Design and implement CI/CD strategies"
            ]
        },
        {
            "company": "Contino",
            "location": "Sydney",
            "position": "Senior DevOps Engineer / Senior Platform Engineer",
            "summary": "Driving adoption of CI/CD for providing business value. Nurturing organisational transformation by leveraging proven processes and technologies",
            "startDate": "2018-04",
            "endDate": "2018-07",
            "keywords": [
                "AWS",
                "DevOps",
                "Consulting"
            ],
            "highlights": [
                "Design and implement CI/CD processes for a large Government project"
            ]
        },
        {
            "breakBefore": true,
            "company": "Commonwealth Bank of Australia",
            "location": "Sydney",
            "position": "Senior DevOps Engineer / Senior Platform Engineer",
            "summary": "Worked with multiple areas of the business, including Netbank, Netbank Mobile, Shared Services, Data Engineering",
            "startDate": "2015-09",
            "endDate": "2018-04",
            "keywords": [
                "AWS",
                "Azure",
                "Bare Metal",
                "PAAS",
                "Kubernetes/Mesos",
                "C#",
                "Golang",
                "Puppet/Ansible/Packet",
                "Vault",
                "CI/CD",
                "Automation"
            ],
            "highlights": [
                "Built a PAAS which runs on over 600 servers",
                "Codified Bare Metal deployments",
                "Increased productivity for development teams using CI/CD practices",
                "Enabled teams to self service in various tools",
                "Trained numerous teams in CI/CD and Testing"
            ]
        },
        {
            "compact": true,
            "company": "Commonwealth Bank of Australia",
            "location": "Sydney",
            "position": "Senior .NET Developer",
            "summary": "Developed .NET Rest APIs to be consumed by CommBanks iOS and Android applications",
            "startDate": "2014-04",
            "endDate": "2015-09",
            "keywords": [
                "Agile",
                "C#",
                "WebAPI",
                "REST"
            ],
            "highlights": [
                "Delivered scheduled payments functionality for the CommBank iOS and Android applications"
            ]
        },
        {
            "compact": true,
            "company": "Viocorp",
            "location": "Sydney",
            "position": "Senior .NET Developer",
            "summary": "Worked on a private video web application like Netflix, which allowed customers to upload videos which then transcoded and distributed the content to their customers. ABC Kids",
            "startDate": "2013-08",
            "endDate": "2014-04",
            "keywords": [
                "Agile",
                "Full-stack",
                "CMS",
                "Umbraco",
                "WCF",
                "JQuery",
                "HTML",
                "CSS"
            ],
            "highlights": [
                "Implemented distributed computing with scale out strategies",
                "Implemented CI/CD for test and production deployments",
                "Provide operations support"
            ]
        },
        {
            "compact": true,
            "company": "Bauer Media (ACP Magazines)",
            "location": "Sydney",
            "position": "Senior .NET Developer",
            "summary": "Full-stack .NET Developer building Umbraco CMS driven websites.",
            "startDate": "2012-08",
            "endDate": "2013-08",
            "keywords": [
                "Agile",
                "Full-stack",
                "CMS",
                "Umbraco",
                "WCF",
                "JQuery",
                "HTML",
                "CSS"
            ],
            "highlights": [
                "Delivered websites that had over 1 million page views per month",
                "Provide operations support"
            ]
        },
        {
            "compact": true,
            "company": "Webcanvas Pty Ltd (Own business)",
            "location": "Sydney",
            "position": "Senior .NET Developer",
            "summary": "Met with customers to delivery IT based services to help grow their businesses. This included CMS based websites and customised internal tools to reduce human error.",
            "startDate": "2010-07",
            "endDate": "2012-08",
            "keywords": [
                "Full-stack",
                "C#",
                "SQL",
                "WebAPI",
                "ASP.NET MVC",
                "CMS",
                "AWS",
                "Azure",
                "Infrastructure",
                "SysAdmin",
                "JQuery",
                "HTML",
                "CSS"
            ],
            "highlights": [
                "Delivered multiple websites for small to medium sized companies.",
                "Provided after hours support.",
                "Run servers in Production for more then 5+ years"
            ]
        },
        {
            "compact": true,
            "company": "Seven Network Pty Ltd",
            "location": "Sydney",
            "position": ".NET Developer",
            "startDate": "2010-03",
            "endDate": "2010-07",
            "summary": "Apart of a large development team (~30 people) building an internal tool named Quatro.",
            "keywords": [
                "Agile",
                "Silverlight",
                "RIA",
                "C#",
                "SQL",
                "MicroService"
            ],
            "highlights": [
                "Successfully delivering 3 core features",
                "Assisting Business Analysts (BA) with design decisions"
            ]
        },
        {
            "compact": true,
            "company": "Interesting Pty Ltd",
            "location": "Sydney",
            "position": ".NET Developer",
            "startDate": "2007-10",
            "endDate": "2010-03",
            "summary": "Created digital media websites for multiple companies include Real Insurance.",
            "keywords": [
                "Agile",
                "Full-stack",
                "SQL",
                "C#",
                "ASP.NET",
                "MVC",
                "Kentico",
                "CMS",
                "WCF",
                "REST",
                "JQuery",
                "HTML",
                "CSS"
            ],
            "highlights": [
                "Delivered over 8 fully customised CMS based web applications",
                "Performed mission-critical production support",
                "Full stack development"
            ]
        }
    ],
    "projects": [
        {
            "company": "Get No_Ops - (www.getnoops.com)",
            "location": "Remote",
            "position": "Co-Founder",
            "summary": "Dev Ops as a Service Platform",
            "startDate": "2021-09",
            "keywords": [
                "AWS",
                "Golang",
                "React.js",
                "CQRS",
                "Event Sourcing",
                "Support",
                "Lean Startup"
            ],
            "highlights": [
                "Built a 10 person company",
                "Created a blueprint pattern for AWS",
                "First class portal to view configuration and operations",
                "World class AWS architecture"
            ]
        },
        {
            "company": "Inflow Technology Services - (www.inflow.pro)",
            "location": "Remote",
            "position": "Founder",
            "summary": "Built a product for distributing mass payments using Lean Startup techniques.",
            "startDate": "2021-09",
            "keywords": [
                "GCP",
                "Golang",
                "React.js",
                "CQRS",
                "Event Sourcing",
                "Support",
                "Lean Startup"
            ],
            "highlights": [
                "Built a 3-5 person company",
                "Moved the core engine from ContextGG into a standalone product",
                "Built and delivered customer portals",
                "Built the Know Your Customer processes",
                "Created the business entity in America"
            ]
        },
        {
            "company": "ContextGG - (www.context.gg)",
            "location": "Remote",
            "position": "Founder",
            "summary": "Built a product to automate the process of Esports tournament payouts and crowdfunding",
            "startDate": "2019-06",
            "keywords": [
                "GCP",
                "Golang",
                "React.js",
                "CQRS",
                "Event Sourcing",
                "Support",
                "Lean Startup"
            ],
            "highlights": [
                "Built the product backlog",
                "Hired multiple developers and designers to build the product",
                "Worked closely with designers and developers to build the product",
                "In charge of strategy and product development",
                "Worked with advisers to build a V.C. pitch"
            ]
        }
    ],
    "volunteer": [
        {
            "organization": "Key Assets",
            "position": "Foster carer",
            "startDate": "2015-09-01",
            "summary": "Full time foster parent of two beautiful children"
        }
    ],
    "education": [
        {
            "institution": "Western Sydney University",
            "url": "https://www.westernsydney.edu.au/",
            "area": "Bachelor of Computer Science",
            "studyType": "Bachelor Degree",
            "startDate": "2003-01-01",
            "endDate": "2007-01-01"
        }
    ],
    "softskills": [
        {
            "name": "Leadership",
            "level": 5
        },
        {
            "name": "Communication",
            "level": 5
        },
        {
            "name": "Teamwork",
            "level": 5
        },
        {
            "name": "Hiring",
            "level": 5
        }
    ],
    "hardskills": [
        {
            "name": "Cloud AWS/GCP",
            "level": 5
        },
        {
            "name": "Architecture",
            "level": 5
        },
        {
            "name": "DevOps",
            "level": 5
        },
        {
            "name": "Golang/NodeJS/ReactJS/C#",
            "level": 5
        },
        {
            "name": "Database Relational/NoSQL",
            "level": 5
        }
    ],
    "interests": [
        {
            "name": "No Ops"
        },
        {
            "name": "A.I. and Machine Learning"
        },
        {
            "name": "Compilers"
        }
    ]
}